mazeexp-0.0.10.dist-info/RECORD
mazeexp-0.0.10.dist-info/top_level.txt
mazeexp-0.0.10.dist-info/METADATA
mazeexp-0.0.10.dist-info/metadata.json
mazeexp-0.0.10.dist-info/DESCRIPTION.rst
mazeexp-0.0.10.dist-info/WHEEL
mazeexp/__init__.py
mazeexp/engine/__init__.py
mazeexp/engine/world.py
mazeexp/engine/message.py
mazeexp/engine/world_rewards.py
mazeexp/engine/config.py
mazeexp/engine/score.py
mazeexp/engine/player.py
mazeexp/engine/generator.py
mazeexp/engine/world_queries.py
mazeexp/engine/collidable.py
mazeexp/engine/world_items.py
mazeexp/engine/mazeexp.py
mazeexp/engine/assets/floor.png
mazeexp/engine/assets/template.tmx
mazeexp/engine/assets/screen_001.jpg
mazeexp/engine/assets/tileset.png
mazeexp/engine/assets/ones.tmx
mazeexp/engine/assets/circle6.png
mazeexp/engine/assets/player7.png
