Metadata-Version: 2.0
Name: mazeexp
Version: 0.0.10
Summary: A maze exploration game engine
Home-page: https://github.com/mryellow/maze_explorer
Author: Mr-Yellow
Author-email: mr-yellow@mr-yellow.com
License: MIT
Keywords: maze,game,maze-explorer,openaigym,openai-gym
Platform: UNKNOWN
Classifier: Development Status :: 3 - Alpha
Classifier: Intended Audience :: Science/Research
Classifier: Topic :: Scientific/Engineering :: Artificial Intelligence
Classifier: License :: OSI Approved :: MIT License
Classifier: Programming Language :: Python :: 2
Classifier: Programming Language :: Python :: 2.6
Classifier: Programming Language :: Python :: 2.7
Requires-Dist: cocos2d
Requires-Dist: pyglet
